polus/__init__.py
polus/polus_render.py
jupyterlab_cors_enabled_polus_render-0.1.1.dist-info/LICENSE
jupyterlab_cors_enabled_polus_render-0.1.1.dist-info/METADATA
jupyterlab_cors_enabled_polus_render-0.1.1.dist-info/WHEEL
jupyterlab_cors_enabled_polus_render-0.1.1.dist-info/RECORD
