Metadata-Version: 2.1
Name: jupyterlab_cors_enabled_polus_render
Version: 0.1.1
Summary: Displays Polus Render dashboard in Jupyter Notebooks.
Home-page: https://github.com/PolusAI/jupyterlab-extensions
Author: Jeff Chen
Author-email: Jeff.Chen@axleinfo.com
Requires-Python: >=3.9
Classifier: Programming Language :: Python :: 3
Classifier: Programming Language :: Python :: 3.9
Classifier: Programming Language :: Python :: 3.10
Classifier: Programming Language :: Python :: 3.11
Classifier: Programming Language :: Python :: 3.12
Requires-Dist: cors-render-server-ext (>=0.1.0)
Project-URL: Repository, https://github.com/PolusAI/jupyterlab-extensions
